server.py
dhan_mcp_server-0.2.0.dist-info/licenses/LICENSE
dhan_mcp_server-0.2.0.dist-info/METADATA
dhan_mcp_server-0.2.0.dist-info/WHEEL
dhan_mcp_server-0.2.0.dist-info/entry_points.txt
dhan_mcp_server-0.2.0.dist-info/top_level.txt
dhan_mcp_server-0.2.0.dist-info/RECORD
