Metadata-Version: 2.4
Name: dhan-mcp-server
Version: 0.2.0
Summary: Model Context Protocol (MCP) server for DhanHQ trading platform
Author-email: Vedhasagaran <vedhasagaran@outlook.com>
License: MIT
Project-URL: Homepage, https://github.com/Vedhasagaran/dhan-mcp-py
Project-URL: Issues, https://github.com/Vedhasagaran/dhan-mcp-py/issues
Keywords: mcp,dhanhq,trading,model-context-protocol
Classifier: Development Status :: 3 - Alpha
Classifier: Intended Audience :: Developers
Classifier: License :: OSI Approved :: MIT License
Classifier: Programming Language :: Python :: 3
Classifier: Programming Language :: Python :: 3.10
Classifier: Programming Language :: Python :: 3.11
Classifier: Programming Language :: Python :: 3.12
Requires-Python: >=3.10
License-File: LICENSE
Requires-Dist: fastmcp>=2.13.0
Requires-Dist: dhanhq>=2.0.2
Requires-Dist: mcp>=1.21.0
Dynamic: license-file
